tqsdk_zq_otg/__init__.py
tqsdk_zq_otg/__version__.py
tqsdk_zq_otg-3.9.0.dist-info/METADATA
tqsdk_zq_otg-3.9.0.dist-info/WHEEL
tqsdk_zq_otg-3.9.0.dist-info/top_level.txt
tqsdk_zq_otg-3.9.0.dist-info/RECORD
