Metadata-Version: 2.1
Name: tqsdk-zq-otg
Version: 3.9.0
Summary: TianQin SDK - zq_otg lib
Home-page: https://www.shinnytech.com/tqsdk
Author: TianQin
Author-email: tianqincn@gmail.com
License: UNKNOWN
Platform: UNKNOWN
Requires-Python: >=3
Requires-Dist: tqsdk (==3.9.0)
